doxyth/__init__.py
doxyth/__main__.py
doxyth/doxyth.py
doxyth/gendoc.py
doxyth/verify.py
doxyth/version.py
doxyth/utils/__init__.py
doxyth/utils/html_builder.py
doxyth/utils/langs.py
doxyth/utils/postprocess.py
doxyth-1.1.0.dist-info/LICENSE
doxyth-1.1.0.dist-info/METADATA
doxyth-1.1.0.dist-info/WHEEL
doxyth-1.1.0.dist-info/top_level.txt
doxyth-1.1.0.dist-info/RECORD
