Metadata-Version: 2.1
Name: doxyth
Version: 1.1.0
Summary: A tool that eases the process of translating documentation to render it with Doxygen
Home-page: https://github.com/BioTheWolff/DoxyTH
Author: Fabien Z.
Author-email: biothewolff@gmx.fr
Maintainer: Fabien Z.
Maintainer-email: biothewolff@gmx.fr
License: MIT
Project-URL: Source Code, https://github.com/BioTheWolff/DoxyTH
Project-URL: Bug Tracker, https://github.com/BioTheWolff/DoxyTH/issues
Platform: UNKNOWN
Classifier: Development Status :: 5 - Production/Stable
Classifier: Environment :: Console
Classifier: Intended Audience :: Developers
Classifier: Topic :: Utilities
Classifier: Programming Language :: Python :: 3
Classifier: License :: OSI Approved :: MIT License
Classifier: Operating System :: OS Independent
Requires-Python: >=3.6
